js_lib_bootstrap5/__init__.py
js_lib_bootstrap5/apps.py
js_lib_bootstrap5/static/js-lib-bootstrap5/css/bootstrap-grid.css
js_lib_bootstrap5/static/js-lib-bootstrap5/css/bootstrap-grid.css.map
js_lib_bootstrap5/static/js-lib-bootstrap5/css/bootstrap-grid.min.css
js_lib_bootstrap5/static/js-lib-bootstrap5/css/bootstrap-grid.min.css.map
js_lib_bootstrap5/static/js-lib-bootstrap5/css/bootstrap-grid.rtl.css
js_lib_bootstrap5/static/js-lib-bootstrap5/css/bootstrap-grid.rtl.css.map
js_lib_bootstrap5/static/js-lib-bootstrap5/css/bootstrap-grid.rtl.min.css
js_lib_bootstrap5/static/js-lib-bootstrap5/css/bootstrap-grid.rtl.min.css.map
js_lib_bootstrap5/static/js-lib-bootstrap5/css/bootstrap-reboot.css
js_lib_bootstrap5/static/js-lib-bootstrap5/css/bootstrap-reboot.css.map
js_lib_bootstrap5/static/js-lib-bootstrap5/css/bootstrap-reboot.min.css
js_lib_bootstrap5/static/js-lib-bootstrap5/css/bootstrap-reboot.min.css.map
js_lib_bootstrap5/static/js-lib-bootstrap5/css/bootstrap-reboot.rtl.css
js_lib_bootstrap5/static/js-lib-bootstrap5/css/bootstrap-reboot.rtl.css.map
js_lib_bootstrap5/static/js-lib-bootstrap5/css/bootstrap-reboot.rtl.min.css
js_lib_bootstrap5/static/js-lib-bootstrap5/css/bootstrap-reboot.rtl.min.css.map
js_lib_bootstrap5/static/js-lib-bootstrap5/css/bootstrap-utilities.css
js_lib_bootstrap5/static/js-lib-bootstrap5/css/bootstrap-utilities.css.map
js_lib_bootstrap5/static/js-lib-bootstrap5/css/bootstrap-utilities.min.css
js_lib_bootstrap5/static/js-lib-bootstrap5/css/bootstrap-utilities.min.css.map
js_lib_bootstrap5/static/js-lib-bootstrap5/css/bootstrap-utilities.rtl.css
js_lib_bootstrap5/static/js-lib-bootstrap5/css/bootstrap-utilities.rtl.css.map
js_lib_bootstrap5/static/js-lib-bootstrap5/css/bootstrap-utilities.rtl.min.css
js_lib_bootstrap5/static/js-lib-bootstrap5/css/bootstrap-utilities.rtl.min.css.map
js_lib_bootstrap5/static/js-lib-bootstrap5/css/bootstrap.css
js_lib_bootstrap5/static/js-lib-bootstrap5/css/bootstrap.css.map
django_js_lib_bootstrap5-5.3.3.1.dist-info/LICENSE
django_js_lib_bootstrap5-5.3.3.1.dist-info/WHEEL
django_js_lib_bootstrap5-5.3.3.1.dist-info/METADATA
django_js_lib_bootstrap5-5.3.3.1.dist-info/RECORD
