Metadata-Version: 2.1
Name: django-js-lib-bootstrap5
Version: 5.3.3.1
Summary: Bootstrap5 Repackaged for Django
Classifier: License :: OSI Approved :: MIT License
